teamvault/apps/accounts/utils.py
teamvault/apps/accounts/urls.py
teamvault/apps/accounts/migrations/0001_initial.py
teamvault/apps/accounts/migrations/0005_rename_usersettings_userprofile.py
teamvault/apps/accounts/migrations/0003_usersettings_avatar.py
teamvault/apps/accounts/migrations/0004_alter_usersettings_hide_deleted_secrets.py
teamvault/apps/accounts/migrations/0002_add_user_settings.py
teamvault/apps/accounts/migrations/__init__.py
teamvault/apps/accounts/forms.py
teamvault/apps/accounts/auth.py
teamvault/apps/accounts/views.py
teamvault/apps/accounts/context_processors.py
teamvault/apps/accounts/__init__.py
teamvault/apps/accounts/models.py
teamvault/apps/accounts/templates/accounts/logout.html
teamvault/apps/accounts/templates/accounts/user_list.html
teamvault/apps/accounts/templates/accounts/user_detail.html
teamvault/apps/accounts/templates/accounts/_avatar.html
teamvault/apps/accounts/templates/accounts/login.html
teamvault/apps/accounts/templates/accounts/user_settings.html
teamvault/apps/secrets/api/urls.py
teamvault/apps/secrets/api/serializers.py
teamvault/apps/secrets/api/views.py
teamvault/apps/secrets/api/__init__.py
teamvault/apps/secrets/fixtures/test_file_v3_migration_fixtures.json
teamvault/apps/secrets/templatetags/smart_pagination.py
teamvault/apps/secrets/templatetags/__init__.py
teamvault/apps/secrets/utils.py
teamvault/apps/secrets/urls.py
teamvault/apps/secrets/services/revision.py
teamvault/apps/secrets/migrations/0001_initial.py
teamvault/apps/secrets/migrations/0022_secret_last_changed.py
teamvault/apps/secrets/migrations/0030_sharedsecretdata_granted_on.py
teamvault/apps/secrets/migrations/0024_auto_20210824_1203.py
teamvault/apps/secrets/migrations/0014_auto_20170313_1544.py
teamvault/apps/secrets/migrations/0016_auto_20180220_1053.py
teamvault/apps/secrets/migrations/0039_migrate_old_file_saves_into_new_format.py
teamvault/apps/secrets/migrations/0011_remove_secret_search_index.py
teamvault-0.11.6.dist-info/licenses/LICENSE
teamvault-0.11.6.dist-info/WHEEL
teamvault-0.11.6.dist-info/entry_points.txt
teamvault-0.11.6.dist-info/METADATA
teamvault-0.11.6.dist-info/RECORD
