Metadata-Version: 2.4
Name: teamvault
Version: 0.11.6
Summary: Keep your passwords behind the firewall
Keywords: password,safe,manager,sharing
Author: Seibert Group GmbH
License-File: LICENSE
Classifier: Development Status :: 3 - Alpha
Classifier: Environment :: Web Environment
Classifier: Framework :: Django
Classifier: License :: OSI Approved :: GNU General Public License v3 (GPLv3)
Classifier: Natural Language :: English
Classifier: Operating System :: POSIX :: Linux
Classifier: Programming Language :: Python :: 3
Classifier: Programming Language :: Python :: 3.12
Classifier: Programming Language :: Python :: 3.13
Classifier: Topic :: Office/Business
Classifier: Topic :: Security
Requires-Dist: cryptography~=46.0.3
Requires-Dist: django-auth-ldap~=5.2.0
Requires-Dist: django-bootstrap5==25.3
Requires-Dist: django-filter==25.2
Requires-Dist: django-htmx~=1.26.0
Requires-Dist: django-test-migrations>=1.5.0
Requires-Dist: django-webpack-loader~=3.2.2
Requires-Dist: django~=5.2.8
Requires-Dist: djangorestframework~=3.16.1
Requires-Dist: gunicorn~=23.0.0
Requires-Dist: hashids~=1.3.1
Requires-Dist: pyotp~=2.9
Requires-Dist: huey~=2.5.4
Requires-Dist: psycopg~=3.2.13
Requires-Dist: pytz~=2025.2
Requires-Dist: requests~=2.32
Requires-Dist: social-auth-app-django~=5.6.0
Requires-Dist: whitenoise[brotli]~=6.11.0
Requires-Python: >=3.12
Project-URL: Source, https://github.com/seibert-media/teamvault
